lodestone_python_sdk/__init__.py
lodestone_python_sdk/auth_client.py
lodestone_python_sdk/exceptions.py
lodestone_python_sdk-1.0.7.dist-info/METADATA
lodestone_python_sdk-1.0.7.dist-info/WHEEL
lodestone_python_sdk-1.0.7.dist-info/top_level.txt
lodestone_python_sdk-1.0.7.dist-info/RECORD
