Metadata-Version: 2.1
Name: lodestone-python-sdk
Version: 1.0.7
Summary: Auth to tuyoo's Lodestone
Home-page: UNKNOWN
Author: bocai
Author-email: peijianbo@tuyoogame.com
License: UNKNOWN
Platform: UNKNOWN
Requires-Python: >3.2
Requires-Dist: requests
Requires-Dist: urllib3 (<2.0)
